pycocks/__init__.py
pycocks/cocks.py
pycocks/utils.py
pycocks-1.0.dist-info/METADATA
pycocks-1.0.dist-info/WHEEL
pycocks-1.0.dist-info/licenses/LICENSE
pycocks-1.0.dist-info/RECORD
