Metadata-Version: 2.1
Name: pycocks
Version: 1.0
Summary: A Python implementation of Cocks' identity-based encryption (IBE) scheme.
Project-URL: Homepage, https://github.com/cgshep/pycocks
Project-URL: Bug Tracker, https://github.com/cgshep/pycocks/issues
Author-email: Carlton Shepherd <carlton@linux.com>
Classifier: Development Status :: 4 - Beta
Classifier: Intended Audience :: Developers
Classifier: Intended Audience :: Science/Research
Classifier: License :: OSI Approved :: MIT License
Classifier: Operating System :: OS Independent
Classifier: Programming Language :: Python :: 3
Classifier: Topic :: Security :: Cryptography
Requires-Python: >=3.3
Requires-Dist: gmpy2>=2.0.0
Provides-Extra: tests
Requires-Dist: pytest>=7.0; extra == 'tests'
